pyrpan/__init__.py
pyrpan/client.py
pyrpan/exceptions.py
pyrpan/models.py
pyrpan-1.3.0.dist-info/LICENSE
pyrpan-1.3.0.dist-info/WHEEL
pyrpan-1.3.0.dist-info/METADATA
pyrpan-1.3.0.dist-info/RECORD
