Metadata-Version: 2.1
Name: pyrpan
Version: 1.3.0
Summary: An API wrapper for interacting with the RPAN API.
Home-page: https://github.com/b1uejay27/PyRPAN
License: MIT
Author: b1uejay
Author-email: hi@b1uejay.dev
Requires-Python: >=3.10,<4.0
Classifier: License :: OSI Approved :: MIT License
Classifier: Operating System :: OS Independent
Classifier: Programming Language :: Python :: 3
Classifier: Programming Language :: Python :: 3.10
Classifier: Programming Language :: Python :: 3
Classifier: Programming Language :: Python :: 3.10
Classifier: Programming Language :: Python :: 3.9
Classifier: Programming Language :: Python :: Implementation :: CPython
Classifier: Typing :: Typed
Requires-Dist: aiohttp (>=3.8.1,<4.0.0)
Requires-Dist: asyncpraw (>=7.5.0,<8.0.0)
Requires-Dist: requests (>=2.28.0,<3.0.0)
Project-URL: Repository, https://github.com/b1uejay27/PyRPAN
